json_to_py/__init__.py
json_to_py/parser.py
json_to_py/type_information.py
json_to_py-1.0.0.dist-info/licenses/LICENSE
tests/__init__.py
tests/expected_data_classes.py
tests/expected_named_tuples.py
tests/test_parser.py
tests/test_type_information.py
json_to_py-1.0.0.dist-info/METADATA
json_to_py-1.0.0.dist-info/WHEEL
json_to_py-1.0.0.dist-info/top_level.txt
json_to_py-1.0.0.dist-info/RECORD
