Metadata-Version: 2.4
Name: json-to-py
Version: 1.0.0
Summary: Convert JSON to Python dataclasses or namedtuples
Author: Nemo_64
License: MIT
Project-URL: Bug Tracker, https://github.com/MrNemo64/json-to-py/issues
Project-URL: Homepage, https://github.com/MrNemo64/json-to-py
Requires-Python: >=3.7
License-File: LICENSE
Dynamic: license-file
